src/panda_core_data/__init__.py
src/panda_core_data/__version__.py
src/panda_core_data/custom_exceptions.py
src/panda_core_data/data_type.py
src/panda_core_data/model.py
src/panda_core_data/utils.py
src/panda_core_data/data_core_bases/__init__.py
src/panda_core_data/data_core_bases/base_data.py
src/panda_core_data/data_core_bases/data_model.py
src/panda_core_data/data_core_bases/data_template.py
src/panda_core_data/storages/__init__.py
src/panda_core_data/storages/base_db.py
src/panda_core_data/storages/json_db.py
src/panda_core_data/storages/yaml_db.py
panda_core_data-0.0.5.dist-info/LICENSE
panda_core_data-0.0.5.dist-info/METADATA
panda_core_data-0.0.5.dist-info/WHEEL
panda_core_data-0.0.5.dist-info/top_level.txt
panda_core_data-0.0.5.dist-info/RECORD
