Metadata-Version: 2.1
Name: panda-core-data
Version: 0.0.5
Summary: Data management system using plain text files like json and yaml.
Home-page: https://github.com/Cerberus1746/PandaCoreData
Author: Leandro (Cerberus1746) Benedet Garcia
Author-email: leandro.benedet.garcia@gmail.com
License: MIT License
Platform: UNKNOWN
Classifier: Programming Language :: Python :: 3.7
Classifier: Programming Language :: Python :: 3.8
Classifier: Programming Language :: Python :: Implementation :: CPython
Classifier: License :: OSI Approved :: MIT License
Classifier: Operating System :: OS Independent
Classifier: Development Status :: 2 - Pre-Alpha
Classifier: Intended Audience :: Developers
Classifier: Topic :: Software Development
Classifier: Topic :: Software Development :: Libraries
Classifier: Topic :: Utilities
Requires-Python: >=3.7
Requires-Dist: tinydb
Requires-Dist: pyyaml
Provides-Extra: docs
Requires-Dist: sphinx ; extra == 'docs'
Requires-Dist: sphinx-rtd-theme ; extra == 'docs'
Provides-Extra: tests
Requires-Dist: pytest ; extra == 'tests'
Requires-Dist: pytest-pylint ; extra == 'tests'
Requires-Dist: pytest-runner ; extra == 'tests'
Requires-Dist: pylint ; extra == 'tests'
Requires-Dist: python-coveralls ; extra == 'tests'
